anysql/__init__.py
anysql/core.py
anysql/escape.py
anysql/interface.py
anysql/py.typed
anysql/uri.py
anysql/backends/__init__.py
anysql/backends/postgres.py
anysql/backends/pymysql.py
anysql/backends/sqlite.py
anysql-0.0.4.dist-info/METADATA
anysql-0.0.4.dist-info/WHEEL
anysql-0.0.4.dist-info/licenses/LICENSE
anysql-0.0.4.dist-info/RECORD
