Metadata-Version: 2.3
Name: anysql
Version: 0.0.4
Summary: Lightweight, Thread-Safe, Version-Agnostic, SQL Client Implementation
Project-URL: Repository, https://github.com/imgurbot12/anysql.git
Author-email: Andrew C Scott <imgurbot12@gmail.com>
License: The MIT License (MIT)
License-File: LICENSE
Keywords: database,simple,sql,universal
Classifier: Intended Audience :: Developers
Classifier: License :: OSI Approved :: MIT License
Classifier: Operating System :: OS Independent
Classifier: Programming Language :: Python :: 3
Classifier: Programming Language :: Python :: 3.8
Classifier: Programming Language :: Python :: 3.9
Classifier: Programming Language :: Python :: 3.10
Classifier: Programming Language :: Python :: 3.11
Classifier: Programming Language :: Python :: 3.12
Requires-Python: >=3.8
Requires-Dist: contextvars>=2.4
Requires-Dist: pypool3>=0.0.2
Requires-Dist: typing-extensions>=4.12.2
Provides-Extra: mysql
Requires-Dist: pymysql>=1.1.1; extra == 'mysql'
Provides-Extra: postgres
Requires-Dist: psycopg2-binary>=2.9.9; extra == 'postgres'
